amal/__init__.py
amal-0.1.0.dist-info/METADATA
amal-0.1.0.dist-info/WHEEL
amal-0.1.0.dist-info/top_level.txt
amal-0.1.0.dist-info/RECORD
