Metadata-Version: 2.1
Name: amal
Version: 0.1.0
Summary: About Amal Rajan
Home-page: https://github.com/amalrajan/amal
Author: Amal Rajan
Author-email: amalrajan@outlook.com
License: MIT
